README.rst
setup.cfg
setup.py
bin/gwin
bin/gwin_extract_samples
bin/gwin_make_inj_workflow
bin/gwin_make_workflow
bin/gwin_plot_acceptance_rate
bin/gwin_plot_acf
bin/gwin_plot_acl
bin/gwin_plot_gelman_rubin
bin/gwin_plot_geweke
bin/gwin_plot_inj_intervals
bin/gwin_plot_inj_recovery
bin/gwin_plot_movie
bin/gwin_plot_posterior
bin/gwin_plot_prior
bin/gwin_plot_samples
bin/gwin_table_summary
bin/run_gwin
gwin/__init__.py
gwin/burn_in.py
gwin/entropy.py
gwin/gelman_rubin.py
gwin/geweke.py
gwin/likelihood.py
gwin/option_utils.py
gwin/workflow.py
gwin.egg-info/PKG-INFO
gwin.egg-info/SOURCES.txt
gwin.egg-info/dependency_links.txt
gwin.egg-info/requires.txt
gwin.egg-info/top_level.txt
gwin/io/__init__.py
gwin/io/hdf.py
gwin/io/txt.py
gwin/results/__init__.py
gwin/results/scatter_histograms.py
gwin/sampler/__init__.py
gwin/sampler/base.py
gwin/sampler/emcee.py
gwin/sampler/kombine.py
gwin/sampler/mcmc.py
test/test_burn_in.py
test/test_entropy.py
test/test_gwin.py