Metadata-Version: 1.1
Name: gwin
Version: 0.1.0.dev1
Summary: A python package for Bayesian inference of gravitational-wave data
Home-page: https://github.com/gwin/gwin
Author: Collin Capano
Author-email: collin.capano@ligo.org
License: GPLv3
Platform: UNKNOWN
Classifier: Development Status :: 3 - Alpha
Classifier: Programming Language :: Python
Classifier: Programming Language :: Python :: 2
Classifier: Programming Language :: Python :: 2.7
Classifier: Intended Audience :: Science/Research
Classifier: Natural Language :: English
Classifier: Topic :: Scientific/Engineering
Classifier: Topic :: Scientific/Engineering :: Astronomy
Classifier: Topic :: Scientific/Engineering :: Physics
Classifier: License :: OSI Approved :: GNU General Public License v3 (GPLv3)
